hashdate/__init__.py
hashdate/cli.py
hashdate-1.0.3.dist-info/entry_points.txt
hashdate-1.0.3.dist-info/LICENSE
hashdate-1.0.3.dist-info/WHEEL
hashdate-1.0.3.dist-info/METADATA
hashdate-1.0.3.dist-info/RECORD
