Metadata-Version: 2.1
Name: hashdate
Version: 1.0.3
Summary: Datetime to fixed hash. Shortable for lower precision
Home-page: https://github.com/sloev/hashdate
License: MIT
Keywords: hash,datetime,prefix
Author: sloev
Author-email: johanned.valbjorn@gmail.com
Requires-Python: >=3.6,<4.0
Classifier: License :: OSI Approved :: MIT License
Classifier: Programming Language :: Python :: 3
Classifier: Programming Language :: Python :: 3.6
Classifier: Programming Language :: Python :: 3.7
Classifier: Programming Language :: Python :: 3.8
Requires-Dist: colorama (>=0.4.3,<0.5.0)
Requires-Dist: python-dateutil (>=2.8.1,<3.0.0)
Project-URL: Repository, https://github.com/sloev/hashdate
